seabirdscientific/__init__.py
seabirdscientific/cal_coefficients.py
seabirdscientific/contour.py
seabirdscientific/conversion.py
seabirdscientific/eos80_processing.py
seabirdscientific/instrument_data.py
seabirdscientific/interpret_sbs_variable.py
seabirdscientific/processing.py
seabirdscientific/utils.py
seabirdscientific/visualization.py
seabirdscientific-2.7.3.dist-info/licenses/LICENSE
seabirdscientific-2.7.3.dist-info/METADATA
seabirdscientific-2.7.3.dist-info/WHEEL
seabirdscientific-2.7.3.dist-info/top_level.txt
seabirdscientific-2.7.3.dist-info/RECORD
