Metadata-Version: 2.4
Name: seabirdscientific
Version: 2.7.3
Summary: Sea-Bird Scientific Community Toolkit
Author-email: Sea-Bird Scientific <techsupport@seabird.com>, Ryan Anderson <randerson@seabird.com>, Lukas Christensen <lchristensen@seabird.com>, Dane Lucas <dlucas@seabird.com>, Eric Rehm <erehm@seabird.com>, Bruce Rhoades <brhoades@seabird.com>, Jesse Templin <jtemplin@seabird.com>
License-Expression: MIT
Project-URL: Homepage, https://www.seabird.com/software
Project-URL: Repository, https://github.com/Sea-BirdScientific/seabirdscientific
Classifier: Programming Language :: Python :: 3 :: Only
Classifier: Programming Language :: Python :: 3.9
Classifier: Programming Language :: Python :: 3.10
Classifier: Programming Language :: Python :: 3.11
Classifier: Programming Language :: Python :: 3.12
Requires-Python: >=3.9
License-File: LICENSE
Requires-Dist: gsw
Requires-Dist: matplotlib
Requires-Dist: numpy
Requires-Dist: pandas
Requires-Dist: plotly>=6.0.0
Requires-Dist: scipy
Provides-Extra: dev
Requires-Dist: build; extra == "dev"
Requires-Dist: nbconvert[webpdf]; extra == "dev"
Requires-Dist: nbformat; extra == "dev"
Requires-Dist: notebook; extra == "dev"
Requires-Dist: pytest; extra == "dev"
Requires-Dist: pytest-cov; extra == "dev"
Requires-Dist: ruff; extra == "dev"
Requires-Dist: kaleido; extra == "dev"
Dynamic: license-file
